pyinstmain.py
yaas/__init__.py
yaas/__main__.py
yaas/app.py
yaas/worker.py
yaas-0.6.10.dist-info/licenses/LICENSE
yturl2mp3/__init__.py
yturl2mp3/__main__.py
yturl2mp3/config.py
yturl2mp3/helpers.py
yturl2mp3/yturl2mp3.py
yaas-0.6.10.dist-info/METADATA
yaas-0.6.10.dist-info/WHEEL
yaas-0.6.10.dist-info/entry_points.txt
yaas-0.6.10.dist-info/top_level.txt
yaas-0.6.10.dist-info/RECORD
