Metadata-Version: 2.4
Name: yaas
Version: 0.6.10
Summary: A tool to split video soundtracks into separate tracks using OpenUnmix
Author-email: Gaël de Chalendar <kleagg@gmail.com>
License: Mozilla Public License Version 2.0
Project-URL: Homepage, https://github.com/kleag/yaas
Keywords: audio,video,track,split,gui,qt
Classifier: Programming Language :: Python :: 3
Classifier: License :: OSI Approved :: Mozilla Public License 2.0 (MPL 2.0)
Classifier: Operating System :: OS Independent
Classifier: Topic :: Multimedia :: Sound/Audio
Classifier: Topic :: Multimedia :: Sound/Audio :: Capture/Recording
Classifier: Topic :: Multimedia :: Sound/Audio :: Conversion
Classifier: Topic :: Multimedia :: Video
Classifier: Topic :: Multimedia :: Video :: Conversion
Requires-Python: <3.13,>=3.8
License-File: LICENSE
Requires-Dist: PySide6>=6.7.1
Requires-Dist: ffmpeg>=1.4
Requires-Dist: numpy==1.26.4
Requires-Dist: pydub>=0.25.1
Requires-Dist: torch==2.3.1
Requires-Dist: torchaudio>=2.1.0
Requires-Dist: openunmix>=1.3.0
Requires-Dist: pytubefix>=8.12.1
Requires-Dist: moviepy>=1.0.3
Requires-Dist: PySoundFile>=0.9.0.post1
Requires-Dist: moviepy==1.0.3
Requires-Dist: audioop-lts>=2.3.1
Dynamic: license-file
